reactive_manim/__init__.py
reactive_manim/src/animation.py
reactive_manim/src/dynamic_mobject.py
reactive_manim/src/dynamic_tex_mobject.py
reactive_manim/src/events.py
reactive_manim/src/helpers.py
reactive_manim/src/interceptors.py
reactive_manim/src/macros.py
reactive_manim/src/managers.py
reactive_manim/src/numpy_mobject_array.py
reactive_manim/src/scene.py
reactive_manim/src/manim_src/composition.py
reactive_manim-0.0.4.dist-info/LICENSE
reactive_manim-0.0.4.dist-info/METADATA
reactive_manim-0.0.4.dist-info/WHEEL
reactive_manim-0.0.4.dist-info/top_level.txt
reactive_manim-0.0.4.dist-info/RECORD
