Metadata-Version: 2.1
Name: reactive-manim
Version: 0.0.4
Summary: A component library for ManimCE, supporting component composition and automatic animation. Supports declarative syntax for writing components inspired by React.js.
Home-page: https://github.com/philip-murray/reactive-manim
Author: Philip Murray
Author-email: philipmurray.code@gmail.com
Requires-Python: >=3.8
License-File: LICENSE
Requires-Dist: manim >=0.18.1
